eao/__init__.py
eao/__main__.py
eao/config.py
eao/evaluator.py
eao/individual.py
eao/logger.py
eao/logging.py
eao/optimizer.py
eao-0.8.dist-info/LICENSE.md
eao-0.8.dist-info/METADATA
eao-0.8.dist-info/WHEEL
eao-0.8.dist-info/top_level.txt
eao-0.8.dist-info/RECORD
