Metadata-Version: 2.1
Name: eao
Version: 0.8
Summary: Evolutionary Optimization
Home-page: https://github.com/smuecke/eao
Author: Sascha Mücke
Author-email: sascha.muecke@tu-dortmund.de
License: GNU GPLv3
Keywords: evolution,evolutionary,algorithm,optimization,genetic
Platform: UNKNOWN
Requires-Python: >=3.5
Requires-Dist: numpy
Requires-Dist: tqdm
